{
  "instance": "Clustered_large_200_9",
  "feasible": true,
  "constraints": {
    "total_routes": 7,
    "total_distance": 5453.305982105284,
    "total_time": 24758.72030158441,
    "vehicles_used": 7,
    "route_details": [
      {
        "route": [
          0,
          61,
          67,
          16,
          133,
          108,
          30,
          60,
          162,
          70,
          99,
          94,
          173,
          72,
          122,
          188,
          11,
          142,
          161,
          196,
          24,
          92,
          49,
          160,
          117,
          82,
          17,
          7,
          170,
          165,
          58,
          178,
          66,
          52,
          105,
          136,
          28,
          0
        ],
        "num_customers": 36
      },
      {
        "route": [
          0,
          14,
          171,
          63,
          198,
          102,
          116,
          8,
          13,
          12,
          73,
          32,
          155,
          181,
          123,
          124,
          88,
          56,
          53,
          27,
          180,
          31,
          192,
          0
        ],
        "num_customers": 22
      },
      {
        "route": [
          0,
          42,
          148,
          110,
          139,
          2,
          143,
          126,
          71,
          5,
          193,
          20,
          194,
          190,
          25,
          138,
          91,
          158,
          127,
          90,
          80,
          199,
          101,
          145,
          48,
          128,
          29,
          159,
          83,
          68,
          46,
          0
        ],
        "num_customers": 30
      },
      {
        "route": [
          0,
          182,
          74,
          93,
          103,
          118,
          125,
          112,
          45,
          77,
          57,
          113,
          131,
          169,
          84,
          150,
          185,
          141,
          81,
          130,
          120,
          109,
          95,
          129,
          36,
          86,
          0
        ],
        "num_customers": 25
      },
      {
        "route": [
          0,
          104,
          164,
          55,
          76,
          26,
          140,
          115,
          97,
          18,
          59,
          37,
          100,
          153,
          96,
          152,
          10,
          33,
          149,
          54,
          156,
          44,
          79,
          23,
          106,
          151,
          98,
          0
        ],
        "num_customers": 26
      },
      {
        "route": [
          0,
          195,
          132,
          144,
          146,
          47,
          186,
          184,
          189,
          75,
          172,
          69,
          85,
          78,
          1,
          166,
          191,
          43,
          34,
          121,
          135,
          157,
          111,
          137,
          174,
          64,
          6,
          197,
          50,
          187,
          0
        ],
        "num_customers": 29
      },
      {
        "route": [
          0,
          107,
          4,
          179,
          35,
          89,
          15,
          62,
          9,
          19,
          175,
          65,
          183,
          147,
          3,
          154,
          168,
          200,
          51,
          41,
          21,
          177,
          134,
          87,
          119,
          163,
          22,
          38,
          176,
          114,
          39,
          40,
          167,
          0
        ],
        "num_customers": 32
      }
    ],
    "errors": [],
    "missing_customers": [],
    "duplicate_customers": []
  },
  "evaluation": {
    "load_variance": 7326.530612244897,
    "spatial_variance": 93.10204081632654,
    "total_distance": 5453.305982105284,
    "total_time": 24758.72030158441,
    "vehicles_used": 7,
    "objective": 11055.510437815557
  }
}