{
  "instance": "Random_tight_200_15",
  "feasible": true,
  "constraints": {
    "total_routes": 23,
    "total_distance": 6024.138703382791,
    "total_time": 11427.128949707601,
    "vehicles_used": 23,
    "route_details": [
      {
        "route": [
          0,
          155,
          18,
          35,
          176,
          165,
          69,
          169,
          101,
          154,
          119,
          0
        ],
        "num_customers": 10
      },
      {
        "route": [
          0,
          196,
          57,
          38,
          173,
          13,
          84,
          138,
          42,
          139,
          53,
          146,
          0
        ],
        "num_customers": 11
      },
      {
        "route": [
          0,
          7,
          41,
          143,
          131,
          180,
          9,
          0
        ],
        "num_customers": 6
      },
      {
        "route": [
          0,
          141,
          129,
          71,
          175,
          100,
          177,
          52,
          24,
          0
        ],
        "num_customers": 8
      },
      {
        "route": [
          0,
          73,
          145,
          2,
          128,
          34,
          6,
          83,
          45,
          0
        ],
        "num_customers": 8
      },
      {
        "route": [
          0,
          87,
          124,
          134,
          103,
          185,
          148,
          113,
          1,
          14,
          0
        ],
        "num_customers": 9
      },
      {
        "route": [
          0,
          46,
          164,
          54,
          89,
          125,
          65,
          29,
          96,
          174,
          110,
          0
        ],
        "num_customers": 10
      },
      {
        "route": [
          0,
          157,
          188,
          184,
          153,
          166,
          193,
          186,
          33,
          167,
          70,
          107,
          75,
          0
        ],
        "num_customers": 12
      },
      {
        "route": [
          0,
          4,
          15,
          94,
          151,
          58,
          144,
          191,
          43,
          198,
          59,
          0
        ],
        "num_customers": 10
      },
      {
        "route": [
          0,
          55,
          67,
          36,
          137,
          68,
          130,
          117,
          25,
          182,
          28,
          91,
          0
        ],
        "num_customers": 11
      },
      {
        "route": [
          0,
          147,
          93,
          199,
          66,
          181,
          111,
          112,
          60,
          81,
          149,
          0
        ],
        "num_customers": 10
      },
      {
        "route": [
          0,
          106,
          85,
          12,
          19,
          178,
          127,
          23,
          22,
          47,
          82,
          74,
          10,
          32,
          0
        ],
        "num_customers": 13
      },
      {
        "route": [
          0,
          158,
          3,
          5,
          133,
          195,
          49,
          160,
          79,
          156,
          172,
          11,
          197,
          0
        ],
        "num_customers": 12
      },
      {
        "route": [
          0,
          63,
          44,
          86,
          64,
          109,
          116,
          78,
          61,
          150,
          0
        ],
        "num_customers": 9
      },
      {
        "route": [
          0,
          120,
          51,
          123,
          21,
          31,
          126,
          50,
          0
        ],
        "num_customers": 7
      },
      {
        "route": [
          0,
          30,
          20,
          163,
          104,
          62,
          194,
          142,
          159,
          102,
          189,
          77,
          108,
          0
        ],
        "num_customers": 12
      },
      {
        "route": [
          0,
          168,
          92,
          48,
          161,
          162,
          76,
          17,
          200,
          192,
          0
        ],
        "num_customers": 9
      },
      {
        "route": [
          0,
          80,
          27,
          135,
          95,
          39,
          179,
          190,
          72,
          56,
          0
        ],
        "num_customers": 9
      },
      {
        "route": [
          0,
          140,
          152,
          118,
          88,
          183,
          99,
          121,
          90,
          0
        ],
        "num_customers": 8
      },
      {
        "route": [
          0,
          132,
          26,
          8,
          122,
          171,
          170,
          40,
          105,
          0
        ],
        "num_customers": 8
      },
      {
        "route": [
          0,
          187,
          115,
          16,
          98,
          136,
          114,
          37,
          97,
          0
        ],
        "num_customers": 8
      },
      {
        "route": [
          0,
          0
        ],
        "num_customers": 0
      },
      {
        "route": [
          0,
          0
        ],
        "num_customers": 0
      }
    ],
    "errors": [],
    "missing_customers": [],
    "duplicate_customers": []
  },
  "evaluation": {
    "load_variance": 2935.5841209829873,
    "spatial_variance": 13.270321361058603,
    "total_distance": 6024.138703382791,
    "total_time": 11427.128949707601,
    "vehicles_used": 23,
    "objective": 6318.861528470202
  }
}